gemini/__init__.py
gemini/claude_integration.py
gemini/codecommon.py
gemini/config.py
gemini/gemini_integration.py
gemini/mistral_integration.py
gemini/openai_integration.py
llm_testing-1.5.9.dist-info/LICENSE
llm_testing-1.5.9.dist-info/METADATA
llm_testing-1.5.9.dist-info/WHEEL
llm_testing-1.5.9.dist-info/top_level.txt
llm_testing-1.5.9.dist-info/RECORD
