Metadata-Version: 2.1
Name: llm-testing
Version: 1.5.9
Summary: A package for generating code using various AI models.
Home-page: https://github.com/yourusername/your_package
Author: Your Name
Author-email: your.email@example.com
Classifier: Programming Language :: Python :: 3
Classifier: License :: OSI Approved :: MIT License
Classifier: Operating System :: OS Independent
Requires-Python: >=3.6
License-File: LICENSE
Requires-Dist: google-generativeai
Requires-Dist: openai
